Custom_Library/Custom_Library.py
Custom_Library/__init__.py
Custom_Library-0.0.2.dist-info/LICENSE.txt
Custom_Library-0.0.2.dist-info/METADATA
Custom_Library-0.0.2.dist-info/WHEEL
Custom_Library-0.0.2.dist-info/top_level.txt
Custom_Library-0.0.2.dist-info/RECORD
