Metadata-Version: 2.1
Name: Custom-Library
Version: 0.0.2
Summary: Custom Library
Home-page: https://github.com/carolineshewchuk/RepoA/Custom_Library
Author: carolineshewchuk
Author-email: caroline.shewchuk@gmail.com
License: UNKNOWN
Platform: UNKNOWN
Classifier: Programming Language :: Python :: 3
Classifier: License :: OSI Approved :: MIT License
Classifier: Operating System :: OS Independent
Requires-Python: >=3.6
